toishi.py
toishi-0.1.2.dist-info/LICENSE
toishi-0.1.2.dist-info/METADATA
toishi-0.1.2.dist-info/WHEEL
toishi-0.1.2.dist-info/entry_points.txt
toishi-0.1.2.dist-info/RECORD
