Metadata-Version: 2.1
Name: toishi
Version: 0.1.2
Summary: 日本語テキストのフォーマッター。名称は日本の伝統的な刃物の研ぎに使用される砥石(toishi)をモチーフにしています
Home-page: https://github.com/mtb-beta/toishi
License: MIT
Author: Tatsuya Matoba
Author-email: tatsuya.matoba.wk.jp@gmail.com
Requires-Python: >=3.12,<4.0
Classifier: License :: OSI Approved :: MIT License
Classifier: Programming Language :: Python :: 3
Classifier: Programming Language :: Python :: 3.12
Requires-Dist: click (>=8.1.7,<9.0.0)
Requires-Dist: pytest-watch (>=4.2.0,<5.0.0)
Requires-Dist: ruff (>=0.1.9,<0.2.0)
Project-URL: Repository, https://github.com/mtb-beta/toishi
